pelecanus/__init__.py
pelecanus/exceptions.py
pelecanus/pelicanjson.py
pelecanus/toolbox.py
pelecanus-0.5.3.dist-info/LICENSE
pelecanus-0.5.3.dist-info/WHEEL
pelecanus-0.5.3.dist-info/METADATA
pelecanus-0.5.3.dist-info/RECORD
